fastchain/__init__.py
fastchain/__main__.py
fastchain/cli.py
fastchain/main.py
fastchain/api/__init__.py
fastchain/core/__init__.py
fastchain/core/config/__init__.py
fastchain/core/config/constants.py
fastchain/core/config/enums.py
fastchain/core/config/local_settings.py
fastchain/core/config/path_settings.py
fastchain/core/config/runtime_store.py
fastchain/core/config/settings_manager.py
fastchain/core/db/__init__.py
fastchain/core/db/mongo/__init__.py
fastchain/core/db/mongo/config.py
fastchain/core/db/mongo/manager.py
fastchain/core/db/mongo/registry.py
fastchain/core/db/redis/__init__.py
fastchain/core/db/redis/config.py
fastchain/core/db/redis/manager.py
fastchain/core/db/relational/__init__.py
fastchain/core/db/relational/config.py
fastchain/core/db/relational/manager.py
fastchain/core/db/relational/models.py
fastchain/core/db/vector/__init__.py
fastchain/core/db/vector/es/__init__.py
fastchain/core/db/vector/es/config.py
fastchain/core/db/vector/es/manager.py
fastchain/core/listeners/__init__.py
fastchain/core/listeners/audit.py
fastchain/core/llm/__init__.py
fastchain/core/llm/manager.py
fastchain/core/llm/service.py
fastchain/core/llm/types.py
fastchain/core/llm/base/__init__.py
fastchain/core/llm/base/callback.py
fastchain/core/llm/base/config.py
fastchain/core/llm/drivers/__init__.py
fastchain/core/llm/drivers/china_unicom.py
fastchain/core/llm/drivers/openai.py
fastchain/core/llm/prompts/__init__.py
fastchain/core/llm/prompts/manager.py
fastchain/core/llm/prompts/schema.py
fastchain/core/llm/utils/__init__.py
fastchain/core/llm/utils/parsers.py
fastchain/core/logging/__init__.py
fastchain/core/logging/logger.py
fastchain/core/monitor/__init__.py
fastchain/core/monitor/metrics.py
fastchain/core/resources/__init__.py
fastchain/core/resources/apollo.py
fastchain/core/resources/base.py
fastchain/core/resources/events.py
fastchain/core/resources/limits.py
fastchain/core/resources/watcher.py
fastchain/core/scheduler/__init__.py
fastchain_cucc-0.1.3.dist-info/METADATA
fastchain_cucc-0.1.3.dist-info/WHEEL
fastchain_cucc-0.1.3.dist-info/entry_points.txt
fastchain_cucc-0.1.3.dist-info/licenses/LICENSE
fastchain_cucc-0.1.3.dist-info/RECORD
