Metadata-Version: 2.4
Name: fastchain-cucc
Version: 0.1.3
Summary: Enterprise-ready FastChain distribution (CUCC)
Project-URL: Homepage, https://example.com
Project-URL: Repository, https://example.com
Author-email: CUCC <noreply@example.com>
License: MIT License
License-File: LICENSE
Classifier: License :: OSI Approved :: MIT License
Classifier: Operating System :: OS Independent
Classifier: Programming Language :: Python :: 3
Classifier: Programming Language :: Python :: 3 :: Only
Requires-Python: >=3.12
Requires-Dist: aiohttp>=3.13.3
Requires-Dist: aiosqlite>=0.22.1
Requires-Dist: apscheduler>=3.11.2
Requires-Dist: beanie>=2.0.1
Requires-Dist: dynaconf>=3.2.12
Requires-Dist: elasticsearch<9.0.0
Requires-Dist: fastapi>=0.123.10
Requires-Dist: httpx>=0.28.1
Requires-Dist: jinja2>=3.1.6
Requires-Dist: langchain-core>=1.1.2
Requires-Dist: langchain-openai>=1.1.1
Requires-Dist: loguru>=0.7.3
Requires-Dist: motor>=3.7.1
Requires-Dist: prometheus-client>=0.23.1
Requires-Dist: pydantic>=2.12.5
Requires-Dist: pyyaml>=6.0.3
Requires-Dist: redis>=7.1.0
Requires-Dist: sqlalchemy[asyncio]>=2.0.45
Requires-Dist: uvicorn>=0.38.0
